lektricowifi/__init__.py
lektricowifi/exceptions.py
lektricowifi/lektricowifi.py
lektricowifi/models.py
lektricowifi-0.0.272.dist-info/LICENSE
lektricowifi-0.0.272.dist-info/METADATA
lektricowifi-0.0.272.dist-info/WHEEL
lektricowifi-0.0.272.dist-info/top_level.txt
lektricowifi-0.0.272.dist-info/RECORD
