Metadata-Version: 2.1
Name: lektricowifi
Version: 0.0.272
Summary: Communication with Lektrico's chargers
Home-page: https://lektri.co
Author: Lektrico
Author-email: mihaela@civitronic.ro
Project-URL: Bug Tracker, https://lektri.co
Classifier: Programming Language :: Python :: 3
Classifier: License :: OSI Approved :: MIT License
Classifier: Operating System :: OS Independent
Requires-Python: >=3.6
License-File: LICENSE
